examples/__init__.py
examples/my_module.py
py2gift/__init__.py
py2gift/_modidx.py
py2gift/_nbdev.py
py2gift/core.py
py2gift/file.py
py2gift/hash.py
py2gift/input_file.py
py2gift/markdown.py
py2gift/notebook.py
py2gift/question.py
py2gift/tex.py
py2gift/time.py
py2gift/util.py
py2gift-0.0.6.2.dist-info/LICENSE
py2gift-0.0.6.2.dist-info/METADATA
py2gift-0.0.6.2.dist-info/WHEEL
py2gift-0.0.6.2.dist-info/entry_points.txt
py2gift-0.0.6.2.dist-info/top_level.txt
py2gift-0.0.6.2.dist-info/RECORD
