Metadata-Version: 2.2
Name: py2gift
Version: 0.0.6.2
Summary: Make input files for gift-wrapper programmatically
Home-page: https://github.com/manuvazquez/py2gift/tree/master/
Author: Manuel A. Vázquez
Author-email: manuavazquez@gmail.com
License: Apache Software License 2.0
Keywords: gift moodle python
Classifier: Development Status :: 3 - Alpha
Classifier: Intended Audience :: Developers
Classifier: Natural Language :: English
Classifier: Programming Language :: Python :: 3.10
Classifier: License :: OSI Approved :: Apache Software License
Requires-Python: >=3.10
License-File: LICENSE
Requires-Dist: numpy
Requires-Dist: pandas
Requires-Dist: matplotlib
Requires-Dist: ruamel.yaml
Requires-Dist: ipython
Requires-Dist: gift-wrapper
Provides-Extra: dev
Dynamic: author
Dynamic: author-email
Dynamic: classifier
Dynamic: description
Dynamic: description-content-type
Dynamic: home-page
Dynamic: keywords
Dynamic: license
Dynamic: provides-extra
Dynamic: requires-dist
Dynamic: requires-python
Dynamic: summary
